FlyDB
